initnative.py
nativecommon-10.dist-info/COPYING
nativecommon-10.dist-info/METADATA
nativecommon-10.dist-info/WHEEL
nativecommon-10.dist-info/entry_points.txt
nativecommon-10.dist-info/top_level.txt
nativecommon-10.dist-info/RECORD
