Metadata-Version: 2.1
Name: nativecommon
Version: 10
Summary: Common code of projects with native parts
Home-page: https://github.com/combatopera/nativecommon
Author: Andrzej Cichocki
License: UNKNOWN
Platform: UNKNOWN
License-File: COPYING
Requires-Dist: Cython (>=0.29.21)
